aind_metadata_mcp/__init__.py
aind_metadata_mcp/data_access_server.py
aind_metadata_mcp/resources/__init__.py
aind_metadata_mcp/resources/aind_api_prompt.txt
aind_metadata_mcp/resources/high_level_schema.txt
aind_metadata_mcp/resources/load_nwbfile.txt
aind_metadata_mcp-0.5.1.dist-info/licenses/LICENSE
aind_metadata_mcp-0.5.1.dist-info/METADATA
aind_metadata_mcp-0.5.1.dist-info/WHEEL
aind_metadata_mcp-0.5.1.dist-info/entry_points.txt
aind_metadata_mcp-0.5.1.dist-info/top_level.txt
aind_metadata_mcp-0.5.1.dist-info/RECORD
