Metadata-Version: 2.4
Name: aind-metadata-mcp
Version: 0.5.1
Summary: MCP server for AIND metadata
Author: Allen Institute for Neural Dynamics
License: MIT
Classifier: Programming Language :: Python :: 3
Requires-Python: >=3.11
License-File: LICENSE
Requires-Dist: aind-data-access-api
Requires-Dist: fastmcp
Requires-Dist: hdmf-zarr>=0.11.1
Requires-Dist: langchain-core>=0.3.60
Requires-Dist: pydantic>=2.11.4
Requires-Dist: suffix-trees>=0.3.0
Provides-Extra: dev
Requires-Dist: black; extra == "dev"
Requires-Dist: coverage; extra == "dev"
Requires-Dist: flake8; extra == "dev"
Requires-Dist: interrogate; extra == "dev"
Requires-Dist: isort; extra == "dev"
Requires-Dist: Sphinx; extra == "dev"
Requires-Dist: furo; extra == "dev"
Dynamic: license-file
